{"background":{"enable":false,"expandScale":[0.0,0.0],"fill":{"alpha":1.0,"content":{"gradient":{"alpha":[1.0,1.0],"angle":90.0,"color":[[1.0,1.0,1.0],[0.686274528503418,0.686274528503418,0.686274528503418]],"mode":"character","percent":[0.0,1.0],"style":"linear"},"render_type":"solid","solid":{"alpha":1.0,"color":[1.0,0.0,0.0]},"texture":{"alpha":1.0,"angle":90.0,"blend":"no","flip":[false,false],"path":"","range":4,"scale":1.0,"stretchMode":"fit","wrapMode":"repeat"}}},"offsetScale":[0.0,0.0],"roundnessScale":0.3},"fill":{"alpha":1.0,"content":{"gradient":{"alpha":[1.0,1.0],"angle":90.0,"color":[[1.0,1.0,1.0],[0.686274528503418,0.686274528503418,0.686274528503418]],"mode":"character","percent":[0.0,1.0],"style":"linear"},"render_type":"texture","solid":{"alpha":1.0,"color":[1.0,1.0,1.0]},"texture":{"alpha":1.0,"angle":0.0,"blend":"no","flip":[false,false],"path":"1774082422507.png","range":1,"scale":1.0,"stretchMode":"fit","wrapMode":"repeat"}}},"inner_shadows":[],"shadows":[{"alpha":1.0,"angle":-45.0,"content":{"gradient":{"alpha":[1.0,1.0],"angle":90.0,"color":[[1.0,1.0,1.0],[0.686274528503418,0.686274528503418,0.686274528503418]],"mode":"character","percent":[0.0,1.0],"style":"linear"},"render_type":"solid","solid":{"alpha":1.0,"color":[0.0,0.0,0.0]},"texture":{"alpha":1.0,"angle":90.0,"blend":"no","flip":[false,false],"path":"","range":4,"scale":1.0,"stretchMode":"fit","wrapMode":"repeat"}},"diffuse":0.0,"distance":2.0,"enable":true,"strokes":[{"alpha":1.0,"content":{"gradient":{"alpha":[1.0,1.0],"angle":90.0,"color":[[1.0,1.0,1.0],[0.686274528503418,0.686274528503418,0.686274528503418]],"mode":"character","percent":[0.0,1.0],"style":"linear"},"render_type":"solid","solid":{"alpha":1.0,"color":[0.0,0.0,0.0]},"texture":{"alpha":1.0,"angle":90.0,"blend":"no","flip":[false,false],"path":"","range":4,"scale":1.0,"stretchMode":"fit","wrapMode":"repeat"}},"enable":true,"mode":0,"width":0.018}],"thickness_projection_angle":45.0,"thickness_projection_distance":15.0,"thickness_projection_enable":false},{"alpha":1.0,"angle":-45.0,"content":{"gradient":{"alpha":[1.0,1.0],"angle":90.0,"color":[[1.0,1.0,1.0],[0.686274528503418,0.686274528503418,0.686274528503418]],"mode":"character","percent":[0.0,1.0],"style":"linear"},"render_type":"solid","solid":{"alpha":1.0,"color":[1.0,0.8980392217636108,0.0]},"texture":{"alpha":1.0,"angle":90.0,"blend":"no","flip":[false,false],"path":"","range":4,"scale":1.0,"stretchMode":"fit","wrapMode":"repeat"}},"diffuse":0.0,"distance":2.0,"enable":true,"strokes":[{"alpha":1.0,"content":{"gradient":{"alpha":[1.0,1.0],"angle":90.0,"color":[[1.0,1.0,1.0],[0.686274528503418,0.686274528503418,0.686274528503418]],"mode":"character","percent":[0.0,1.0],"style":"linear"},"render_type":"solid","solid":{"alpha":1.0,"color":[1.0,0.8980392217636108,0.0]},"texture":{"alpha":1.0,"angle":90.0,"blend":"no","flip":[false,false],"path":"","range":4,"scale":1.0,"stretchMode":"fit","wrapMode":"repeat"}},"enable":true,"mode":0,"width":0.09},{"alpha":1.0,"content":{"gradient":{"alpha":[1.0,1.0],"angle":90.0,"color":[[1.0,1.0,1.0],[0.686274528503418,0.686274528503418,0.686274528503418]],"mode":"character","percent":[0.0,1.0],"style":"linear"},"render_type":"solid","solid":{"alpha":1.0,"color":[1.0,0.4000000059604645,0.0]},"texture":{"alpha":1.0,"angle":90.0,"blend":"no","flip":[false,false],"path":"","range":4,"scale":1.0,"stretchMode":"fit","wrapMode":"repeat"}},"enable":true,"mode":0,"width":0.12},{"alpha":1.0,"content":{"gradient":{"alpha":[1.0,1.0],"angle":90.0,"color":[[1.0,1.0,1.0],[0.686274528503418,0.686274528503418,0.686274528503418]],"mode":"character","percent":[0.0,1.0],"style":"linear"},"render_type":"solid","solid":{"alpha":1.0,"color":[1.0,0.5843137502670288,0.0]},"texture":{"alpha":1.0,"angle":90.0,"blend":"no","flip":[false,false],"path":"","range":4,"scale":1.0,"stretchMode":"fit","wrapMode":"repeat"}},"enable":true,"mode":0,"width":0.148}],"thickness_projection_angle":45.0,"thickness_projection_distance":20.0,"thickness_projection_enable":false},{"alpha":1.0,"angle":-45.0,"content":{"gradient":{"alpha":[1.0,1.0],"angle":90.0,"color":[[1.0,1.0,1.0],[0.686274528503418,0.686274528503418,0.686274528503418]],"mode":"character","percent":[0.0,1.0],"style":"linear"},"render_type":"solid","solid":{"alpha":1.0,"color":[1.0,0.9725490212440491,0.7411764860153198]},"texture":{"alpha":1.0,"angle":90.0,"blend":"no","flip":[false,false],"path":"","range":4,"scale":1.0,"stretchMode":"fit","wrapMode":"repeat"}},"diffuse":0.0,"distance":2.0,"enable":true,"strokes":[{"alpha":1.0,"content":{"gradient":{"alpha":[1.0,1.0],"angle":90.0,"color":[[1.0,1.0,1.0],[0.686274528503418,0.686274528503418,0.686274528503418]],"mode":"character","percent":[0.0,1.0],"style":"linear"},"render_type":"solid","solid":{"alpha":1.0,"color":[1.0,0.9725490212440491,0.7411764860153198]},"texture":{"alpha":1.0,"angle":90.0,"blend":"no","flip":[false,false],"path":"","range":4,"scale":1.0,"stretchMode":"fit","wrapMode":"repeat"}},"enable":true,"mode":0,"width":0.18}],"thickness_projection_angle":45.0,"thickness_projection_distance":20.0,"thickness_projection_enable":false}],"strokes":[{"alpha":1.0,"content":{"gradient":{"alpha":[1.0,1.0],"angle":90.0,"color":[[1.0,1.0,1.0],[0.686274528503418,0.686274528503418,0.686274528503418]],"mode":"character","percent":[0.0,1.0],"style":"linear"},"render_type":"solid","solid":{"alpha":1.0,"color":[0.0,0.0,0.0]},"texture":{"alpha":1.0,"angle":90.0,"blend":"no","flip":[false,false],"path":"","range":4,"scale":1.0,"stretchMode":"fit","wrapMode":"repeat"}},"enable":true,"mode":0,"width":0.03}],"textable":false,"version":3.0,"version_sdk":"16.6.0"}